Workbook

Sheet Tabla 1
A1: Tabla 1. Alineación de Alpura con los objetivos de Danone
A3: Objetivo de la búsqueda | B3: Contribución de Alpura
A4: Incrementar la participación de mercado | B4: La suma pasaría de 3.9% a cerca de 14.7% del mercado lácteo; Danone quedaría segundo, detrás de Lala (21.5%)
A5: Diversificación de productos | B5: Agrega leche UHT, deslactosada, evaporada, crema y quesos, que Danone no fabrica en México
A6: Expansión (nuevos mercados y canales) | B6: Red refrigerada en el canal tradicional (más de 100,000 puntos de venta) para mover yogur y leche en una misma ruta
A7: Reducción de costos y ventaja competitiva | B7: Abasto propio de leche: hoy la red Margarita aporta solo 25% de la leche de Danone en México (Expansión, 2025)
A8: Maximizar el valor de los accionistas | B8: Sinergias estimadas de 800 millones de pesos anuales, siempre que el precio no las transfiera al vendedor
A10: Fuente: elaboración propia con base en Forbes México (2017), América Retail (2025) y Expansión (2025).

Sheet Tabla 2
A1: Tabla 2. Objetivos de búsqueda de Danone
A3: Pregunta | B3: Respuesta para Danone
A4: ¿Industria, productos y mercado? | B4: Lácteos: leche fluida, crema y quesos en México, con presencia nacional
A5: ¿Participación y crecimiento buscados? | B5: Empresa con más de 5% del mercado, para superar 10% y crecer más que el 3–5% anual del plan de Danone
A6: ¿Inversión requerida? | B6: Hasta 24,000 millones de pesos de valor empresa, con flujo propio y deuda
A7: ¿Expansión internacional y país? | B7: No; consolidación en México, quinto mercado del grupo
A8: ¿Riesgo tolerado? | B8: Moderado: se acepta riesgo laboral y regulatorio mitigable, no un riesgo de objeción total por competencia
A10: Fuente: elaboración propia con base en Mascareñas (2019) y Danone (2026).

Sheet Tabla 3
A1: Tabla 3. Revisión de elementos legales
A3: Elemento | B3: Hallazgo en Alpura | C3: Riesgo
A4: Aspectos corporativos | B4: Acta constitutiva de 1970; capital repartido entre ganaderos socios con unión de crédito propia (UAM, s. f.) | C4: Alto: revisar gravámenes sobre acciones, derechos de preferencia y asambleas en el RPPC
A5: Patentes y marcas | B5: Marcas Alpura, Alpura 2000, Frutal y personajes “Cuartitos” | C5: Bajo: confirmar registros vigentes ante el IMPI
A6: Contratos vigentes | B6: Laboral: contrato colectivo con la CROC. Comerciales: suministro con ranchos socios y autoservicios. Bancarios: créditos por 6,500 millones | C6: Medio: cláusulas de cambio de control y precio de la leche a socios
A7: Cumplimiento regulatorio | B7: Permisos de Cofepris, NOM-243-SSA1-2010 y NOM-051 (etiquetado), IMSS y protección civil; notificación a la Comisión Nacional Antimonopolio (Galicia Abogados, 2025) | C7: Medio: sellos en leches saborizadas; posible condición en yogur
A8: Litigios | B8: Conflicto laboral con emplazamiento a huelga en 2025 (Posta, 2025); revisar litigios civiles, mercantiles y fiscales | C8: Medio-alto: pasivo laboral contingente
A9: Cumplimiento fiscal | B9: Verificar opinión de cumplimiento del SAT y declaraciones de los últimos cinco años | C9: Medio: sin información pública
A11: Fuente: elaboración propia con base en Universidad Tecmilenio (s. f.-b), UAM (s. f.) y Posta (2025).

Sheet Tabla 4
A1: Tabla 4. Información financiera estimada de Alpura (millones de pesos)
A3: Concepto | B3: 2023 | C3: 2024 | D3: 2025 | E3: Vertical 2025 | F3: Horizontal 23–25
A4: Ventas netas | B4: 24500 | C4: 26300 | D4: 28100 | E4: =D4/$D$4 -> 1 | F4: =D4/B4-1 -> 0.14693878
A5: Utilidad bruta | B5: 7230 | C5: 7890 | D5: 8430 | E5: =D5/$D$4 -> 0.3 | F5: =D5/B5-1 -> 0.1659751
A6: EBITDA | B6: 2200 | C6: 2450 | D6: 2670 | E6: =D6/$D$4 -> 0.095017794 | F6: =D6/B6-1 -> 0.21363636
A7: Utilidad neta | B7: 455 | C7: 567 | D7: 679 | E7: =D7/$D$4 -> 0.024163701 | F7: =D7/B7-1 -> 0.49230769
A8: Deuda neta | B8: 6800 | C8: 6600 | D8: 6500 | E8: — | F8: =D8/B8-1 -> -0.044117647
A9: Inversión en activos (CapEx) | B9: 1300 | C9: 1600 | D9: 2500 | E9: =D9/$D$4 -> 0.088967972 | F9: =D9/B9-1 -> 0.92307692
A11: Fuente: estimación propia (cifras ficticias). Ventas proyectadas desde 15,000 millones en 2015 (Expansión, 2016)
A12: con un crecimiento promedio de 6.3% anual; márgenes típicos del sector lácteo; capex de 2025 basado en el plan de inversión de 10,000 millones en cuatro años (América Retail, 2025).
A13: Notas: cifras en azul = datos capturados; en negro = fórmulas. Vertical 2025 = concepto / ventas netas 2025. Horizontal 23–25 = (2025 / 2023) − 1. La deuda neta no se expresa como % de ventas.

Sheet Razones financieras Alpura
A1: Razones financieras de Alpura 2025 (cifras estimadas)
A3: Datos base (millones de pesos)
A4: Concepto | D4: Valor | E4: Fuente
A5: Ventas netas 2025 | D5: 28100 | E5: Tabla 4 (estimación propia)
A6: EBITDA 2025 | D6: 2670 | E6: Tabla 4 (estimación propia)
A7: Deuda neta 2025 | D7: 6500 | E7: Tabla 4 (estimación propia)
A8: Margen operativo recurrente de Danone 2025 | D8: 0.134 | E8: Danone (2026)
A9: Límite bancario de deuda neta / EBITDA | D9: 2.5 | E9: Supuesto de referencia del sector
A11: Razones financieras 2025
A12: Categoría | B12: Razón | C12: Fórmula | D12: Resultado 2025 | E12: Interpretación
A13: Liquidez | B13: Razón circulante | C13: Activo circulante / pasivo circulante | D13: 1.3 | E13: Cubre 1.3 pesos de deuda de corto plazo por cada peso que debe.
A14: Liquidez | B14: Prueba ácida | C14: (Activo circulante − inventarios) / pasivo circulante | D14: 0.9 | E14: Sin inventarios no alcanza a cubrir toda su deuda de corto plazo.
A15: Actividad | B15: Días de inventario | C15: Inventario / costo de ventas × 365 | D15: 18 | E15: Rotación alta, propia de productos perecederos.
A16: Actividad | B16: Días de cobro | C16: Cuentas por cobrar / ventas × 365 | D16: 32 | E16: Plazo de crédito típico con autoservicios.
A17: Actividad | B17: Días de pago | C17: Cuentas por pagar / costo de ventas × 365 | D17: 45 | E17: Paga a proveedores después de cobrar a clientes.
A18: Actividad | B18: Ciclo financiero | C18: Días de inventario + días de cobro − días de pago | D18: =D15+D16-D17 -> 5 | E18: Necesita poco capital de trabajo.
A19: Rentabilidad | B19: Margen EBITDA | C19: EBITDA / ventas netas | D19: =D6/D5 -> 0.095017794 | E19: Menor que el margen de Danone: la compra es dilutiva.
A20: Rentabilidad | B20: Diferencia contra Danone | C20: Margen EBITDA Alpura − margen Danone | D20: =D19-D8 -> -0.038982206 | E20: Puntos porcentuales por debajo de Danone.
A21: Apalancamiento | B21: Deuda neta / EBITDA | C21: Deuda neta / EBITDA | D21: =D7/D6 -> 2.4344569 | E21: Cerca del límite bancario.
A22: Apalancamiento | B22: Margen contra el límite | C22: Límite bancario − deuda neta / EBITDA | D22: =D9-D21 -> 0.065543071 | E22: Holgura restante antes del límite.
A24: Flujo de efectivo libre proyectado (millones de pesos)
A25: Año | D25: Flujo libre | E25: Comentario
A26: 2026 | D26: -691 | E26: Negativo por el plan de inversión de 10,000 millones en cuatro años (América Retail, 2025); incluye ISR, capex e incremento en capital de trabajo (ver Tabla 5).
A27: 2027 | D27: -206 | E27: Negativo por el plan de inversión de 10,000 millones en cuatro años (América Retail, 2025); incluye ISR, capex e incremento en capital de trabajo (ver Tabla 5).
A29: Fuente: estimación propia (cifras ficticias); Danone (2026); América Retail (2025).
A30: Notas: cifras en azul = datos capturados (supuestos); en negro = fórmulas. Las razones de liquidez y actividad son supuestos, porque Alpura no publica su balance.

Sheet Tabla 5
A1: Tabla 5. Evaluación financiera de la compra del 100% (millones de pesos)
A2: Costo de capital de 10%; ventas y EBITDA crecen 7% anual; sinergias de 800 millones desde 2029; costos de integración de 1,000 millones; incluye ISR, capex e incremento en capital de trabajo; crecimiento a perpetuidad de 4%.
A4: Técnica | B4: Precio a 9× EBITDA | C4: Precio a 11× EBITDA | D4: Criterio de decisión
A5: Precio pagado (valor empresa) | B5: 24000 | C5: 29400 | D5: EBITDA 2025 × múltiplo, redondeado (2,670 × 9 y × 11)
A6: Valor presente neto (VPN) | B6: ='Supuestos y proyección'!B38-B5 -> 2776.2726 | C6: ='Supuestos y proyección'!B38-C5 -> -2623.7274 | D6: Aceptar si VPN > 0
A7: Tasa interna de retorno (TIR) | B7: =IRR('Flujos de largo plazo'!D5:D305) -> 0.10574743 | C7: =IRR('Flujos de largo plazo'!F5:F305) -> 0.095433079 | D7: Aceptar si TIR > costo de capital (10%)
A8: Recuperación de la inversión | B8: =COUNTIF('Flujos de largo plazo'!E6:E305,"<0")+1 -> 13 | C8: =COUNTIF('Flujos de largo plazo'!G6:G305,"<0")+1 -> 15 | D8: Años para recuperar el precio con flujos sin descontar
A9: Decisión | B9: =IF(AND(B6>0,B7>Costo_capital),"Crea valor","Destruye valor") -> Crea valor | C9: =IF(AND(C6>0,C7>Costo_capital),"Crea valor","Destruye valor") -> Destruye valor | D9: VPN positivo y TIR mayor al costo de capital
A11: Valor presente de los flujos con sinergias | B11: ='Supuestos y proyección'!B38 -> 26776.273 | C11: ='Supuestos y proyección'!B39 -> 10.028567
A13: Fuente: elaboración propia (cifras ficticias). Detalle del cálculo en las hojas "Supuestos y proyección" y "Flujos de largo plazo".

Sheet Supuestos y proyección
A1: Supuestos y proyección del flujo de efectivo libre de Alpura (millones de pesos)
A3: Supuesto | B3: Valor | C3: Comentario
A4: Ventas netas 2025 | B4: 28100 | C4: Tabla 4
A5: EBITDA 2025 | B5: 2670 | C5: Tabla 4
A6: Crecimiento anual de ventas y EBITDA | B6: 0.07 | C6: Supuesto
A7: Costo de capital (tasa de descuento) | B7: 0.1 | C7: Rendimiento mínimo exigido por Danone (supuesto)
A8: Crecimiento a perpetuidad (después de 2030) | B8: 0.04 | C8: Cercano a la inflación de largo plazo (supuesto)
A9: Tasa de ISR | B9: 0.3 | C9: Tasa corporativa en México
A10: Costo de ventas / ventas | B10: 0.7 | C10: Margen bruto de 30% (Tabla 4)
A11: Días de inventario | B11: 18 | C11: Razones financieras 2025
A12: Días de cobro | B12: 32 | C12: Razones financieras 2025
A13: Días de pago | B13: 45 | C13: Razones financieras 2025
A14: Capital de trabajo / ventas | B14: =(B11*B10+B12-B13*B10)/365 -> 0.035890411 | C14: Fórmula: inventario + clientes − proveedores
A17: Proyección del flujo de efectivo libre
A18: Concepto | B18: 2025 (base) | C18: 2026 | D18: 2027 | E18: 2028 | F18: 2029 | G18: 2030
A19: Ventas netas | B19: =B4 -> 28100 | C19: =B19*(1+$B$6) -> 30067 | D19: =C19*(1+$B$6) -> 32171.69 | E19: =D19*(1+$B$6) -> 34423.708 | F19: =E19*(1+$B$6) -> 36833.368 | G19: =F19*(1+$B$6) -> 39411.704
A20: EBITDA de Alpura | B20: =B5 -> 2670 | C20: =B20*(1+$B$6) -> 2856.9 | D20: =C20*(1+$B$6) -> 3056.883 | E20: =D20*(1+$B$6) -> 3270.8648 | F20: =E20*(1+$B$6) -> 3499.8253 | G20: =F20*(1+$B$6) -> 3744.8131
A21: (+) Sinergias | C21: 0 | D21: 300 | E21: 600 | F21: 800 | G21: 800
A22: (−) Costos de integración | C22: 600 | D22: 400 | E22: 0 | F22: 0 | G22: 0
A23: (=) EBITDA ajustado | C23: =C20+C21-C22 -> 2256.9 | D23: =D20+D21-D22 -> 2956.883 | E23: =E20+E21-E22 -> 3870.8648 | F23: =F20+F21-F22 -> 4299.8253 | G23: =G20+G21-G22 -> 4544.8131
A24: (−) Depreciación y amortización | C24: 1000 | D24: 1000 | E24: 1000 | F24: 1150 | G24: 1150
A25: (=) EBIT (utilidad de operación) | C25: =C23-C24 -> 1256.9 | D25: =D23-D24 -> 1956.883 | E25: =E23-E24 -> 2870.8648 | F25: =F23-F24 -> 3149.8253 | G25: =G23-G24 -> 3394.8131
A26: (−) ISR sobre EBIT | C26: =MAX(0,C25)*$B$9 -> 377.07 | D26: =MAX(0,D25)*$B$9 -> 587.0649 | E26: =MAX(0,E25)*$B$9 -> 861.25944 | F26: =MAX(0,F25)*$B$9 -> 944.9476 | G26: =MAX(0,G25)*$B$9 -> 1018.4439
A27: (=) NOPAT (utilidad operativa después de impuestos) | C27: =C25-C26 -> 879.83 | D27: =D25-D26 -> 1369.8181 | E27: =E25-E26 -> 2009.6054 | F27: =F25-F26 -> 2204.8777 | G27: =G25-G26 -> 2376.3692
A28: (+) Depreciación y amortización | C28: =C24 -> 1000 | D28: =D24 -> 1000 | E28: =E24 -> 1000 | F28: =F24 -> 1150 | G28: =G24 -> 1150
A29: (−) Inversión en activos (capex) | C29: 2500 | D29: 2500 | E29: 2500 | F29: 1200 | G29: 1200
A30: Capital de trabajo (saldo) | B30: =B19*$B$14 -> 1008.5205 | C30: =C19*$B$14 -> 1079.117 | D30: =D19*$B$14 -> 1154.6552 | E30: =E19*$B$14 -> 1235.481 | F30: =F19*$B$14 -> 1321.9647 | G30: =G19*$B$14 -> 1414.5022
A31: (−) Incremento en capital de trabajo | C31: =C30-B30 -> 70.596438 | D31: =D30-C30 -> 75.538189 | E31: =E30-D30 -> 80.825862 | F31: =F30-E30 -> 86.483673 | G31: =G30-F30 -> 92.53753
A32: (=) Flujo de efectivo libre | C32: =C27+C28-C29-C31 -> -690.76644 | D32: =D27+D28-D29-D31 -> -205.72009 | E32: =E27+E28-E29-E31 -> 428.7795 | F32: =F27+F28-F29-F31 -> 2068.3941 | G32: =G27+G28-G29-G31 -> 2233.8317
A34: Flujo de efectivo libre 2031 (primer año a perpetuidad) | G34: =(G27+G28-G29)*(1+B8)-G30*B8 -> 2362.8439
A35: Valor terminal en 2030 = FEL 2031 / (costo de capital − crecimiento) | G35: =G34/(B7-B8) -> 39380.731
A36: Factor de descuento | C36: =1/(1+$B$7)^1 -> 0.90909091 | D36: =1/(1+$B$7)^2 -> 0.82644628 | E36: =1/(1+$B$7)^3 -> 0.7513148 | F36: =1/(1+$B$7)^4 -> 0.68301346 | G36: =1/(1+$B$7)^5 -> 0.62092132
A37: Valor presente del flujo (y del valor terminal en 2030) | C37: =(C32)*C36 -> -627.96949 | D37: =(D32)*D36 -> -170.0166 | E37: =(E32)*E36 -> 322.14839 | F37: =(F32)*F36 -> 1412.741 | G37: =(G32+G35)*G36 -> 25839.369
A38: Valor presente total = valor máximo para Danone | B38: =SUM(C37:G37) -> 26776.273
A39: Equivale a (veces EBITDA 2025) | B39: =B38/B5 -> 10.028567
A41: Notas: cifras en azul = supuestos capturados; en negro = fórmulas. Paréntesis = cifras negativas. El ISR se calcula sobre el EBIT; a perpetuidad el capital de trabajo crece al mismo ritmo que las ventas.

Sheet Flujos de largo plazo
A1: Flujos anuales para calcular TIR y recuperación (millones de pesos)
A2: Años 1–5: proyección explícita; desde el año 6 el flujo crece a la tasa de perpetuidad (equivale al valor terminal).
A4: Año | B4: Año calendario | C4: Flujo libre | D4: Flujo escenario A (9×) | E4: Acumulado A | F4: Flujo escenario B (11×) | G4: Acumulado B
A5: 0 | B5: 2025 | D5: =-'Tabla 5'!B5 -> -24000 | E5: =D5 -> -24000 | F5: =-'Tabla 5'!C5 -> -29400 | G5: =F5 -> -29400
A6: 1 | B6: =B5+1 -> 2026 | C6: ='Supuestos y proyección'!C32 -> -690.76644 | D6: =C6 -> -690.76644 | E6: =E5+D6 -> -24690.766 | F6: =C6 -> -690.76644 | G6: =G5+F6 -> -30090.766
A7: 2 | B7: =B6+1 -> 2027 | C7: ='Supuestos y proyección'!D32 -> -205.72009 | D7: =C7 -> -205.72009 | E7: =E6+D7 -> -24896.487 | F7: =C7 -> -205.72009 | G7: =G6+F7 -> -30296.487
A8: 3 | B8: =B7+1 -> 2028 | C8: ='Supuestos y proyección'!E32 -> 428.7795 | D8: =C8 -> 428.7795 | E8: =E7+D8 -> -24467.707 | F8: =C8 -> 428.7795 | G8: =G7+F8 -> -29867.707
A9: 4 | B9: =B8+1 -> 2029 | C9: ='Supuestos y proyección'!F32 -> 2068.3941 | D9: =C9 -> 2068.3941 | E9: =E8+D9 -> -22399.313 | F9: =C9 -> 2068.3941 | G9: =G8+F9 -> -27799.313
A10: 5 | B10: =B9+1 -> 2030 | C10: ='Supuestos y proyección'!G32 -> 2233.8317 | D10: =C10 -> 2233.8317 | E10: =E9+D10 -> -20165.481 | F10: =C10 -> 2233.8317 | G10: =G9+F10 -> -25565.481
A11: 6 | B11: =B10+1 -> 2031 | C11: ='Supuestos y proyección'!G34 -> 2362.8439 | D11: =C11 -> 2362.8439 | E11: =E10+D11 -> -17802.637 | F11: =C11 -> 2362.8439 | G11: =G10+F11 -> -23202.637
A12: 7 | B12: =B11+1 -> 2032 | C12: =C11*(1+'Supuestos y proyección'!$B$8) -> 2457.3576 | D12: =C12 -> 2457.3576 | E12: =E11+D12 -> -15345.28 | F12: =C12 -> 2457.3576 | G12: =G11+F12 -> -20745.28
A13: 8 | B13: =B12+1 -> 2033 | C13: =C12*(1+'Supuestos y proyección'!$B$8) -> 2555.6519 | D13: =C13 -> 2555.6519 | E13: =E12+D13 -> -12789.628 | F13: =C13 -> 2555.6519 | G13: =G12+F13 -> -18189.628
A14: 9 | B14: =B13+1 -> 2034 | C14: =C13*(1+'Supuestos y proyección'!$B$8) -> 2657.878 | D14: =C14 -> 2657.878 | E14: =E13+D14 -> -10131.75 | F14: =C14 -> 2657.878 | G14: =G13+F14 -> -15531.75
A15: 10 | B15: =B14+1 -> 2035 | C15: =C14*(1+'Supuestos y proyección'!$B$8) -> 2764.1931 | D15: =C15 -> 2764.1931 | E15: =E14+D15 -> -7367.5568 | F15: =C15 -> 2764.1931 | G15: =G14+F15 -> -12767.557
A16: 11 | B16: =B15+1 -> 2036 | C16: =C15*(1+'Supuestos y proyección'!$B$8) -> 2874.7608 | D16: =C16 -> 2874.7608 | E16: =E15+D16 -> -4492.7959 | F16: =C16 -> 2874.7608 | G16: =G15+F16 -> -9892.7959
A17: 12 | B17: =B16+1 -> 2037 | C17: =C16*(1+'Supuestos y proyección'!$B$8) -> 2989.7513 | D17: =C17 -> 2989.7513 | E17: =E16+D17 -> -1503.0447 | F17: =C17 -> 2989.7513 | G17: =G16+F17 -> -6903.0447
A18: 13 | B18: =B17+1 -> 2038 | C18: =C17*(1+'Supuestos y proyección'!$B$8) -> 3109.3413 | D18: =C18 -> 3109.3413 | E18: =E17+D18 -> 1606.2967 | F18: =C18 -> 3109.3413 | G18: =G17+F18 -> -3793.7033
A19: 14 | B19: =B18+1 -> 2039 | C19: =C18*(1+'Supuestos y proyección'!$B$8) -> 3233.715 | D19: =C19 -> 3233.715 | E19: =E18+D19 -> 4840.0116 | F19: =C19 -> 3233.715 | G19: =G18+F19 -> -559.98835
A20: 15 | B20: =B19+1 -> 2040 | C20: =C19*(1+'Supuestos y proyección'!$B$8) -> 3363.0636 | D20: =C20 -> 3363.0636 | E20: =E19+D20 -> 8203.0752 | F20: =C20 -> 3363.0636 | G20: =G19+F20 -> 2803.0752
A21: 16 | B21: =B20+1 -> 2041 | C21: =C20*(1+'Supuestos y proyección'!$B$8) -> 3497.5861 | D21: =C21 -> 3497.5861 | E21: =E20+D21 -> 11700.661 | F21: =C21 -> 3497.5861 | G21: =G20+F21 -> 6300.6614
A22: 17 | B22: =B21+1 -> 2042 | C22: =C21*(1+'Supuestos y proyección'!$B$8) -> 3637.4896 | D22: =C22 -> 3637.4896 | E22: =E21+D22 -> 15338.151 | F22: =C22 -> 3637.4896 | G22: =G21+F22 -> 9938.1509
A23: 18 | B23: =B22+1 -> 2043 | C23: =C22*(1+'Supuestos y proyección'!$B$8) -> 3782.9892 | D23: =C23 -> 3782.9892 | E23: =E22+D23 -> 19121.14 | F23: =C23 -> 3782.9892 | G23: =G22+F23 -> 13721.14
... A305: 300 | B305: =B304+1 -> 2325 | C305: =C304*(1+'Supuestos y proyección'!$B$8) -> 2.405674e+08 | D305: =C305 -> 2.405674e+08 | E305: =E304+D305 -> 6.2546732e+09 | F305: =C305 -> 2.405674e+08 | G305: =G304+F305 -> 6.2546678e+09

Sheet Tabla 6
A1: Tabla 6. Opciones de decisión para Danone
A3: Opción | B3: Cuándo aplicaría | C3: Veredicto
A4: Adquirir el 100% ahora | B4: Si el vendedor aceptara 9 veces EBITDA o menos, sin conflicto laboral abierto | C4: No recomendada hoy
A5: Renegociar | B5: Compra de 51–60% a no más de 9 veces EBITDA, opción sobre el resto en 3–5 años y earn-out ligado al EBITDA 2027–2028 | C5: Recomendada
A6: Descartar | B6: Si el precio supera 10 veces EBITDA, si la autoridad exige vender marcas de yogur o si estalla la huelga | C6: Plan de salida: crecer con la red Margarita
A8: Fuente: elaboración propia.
